texpass/__init__.py
texpass/__main__.py
texpass/setup_app.py
texpass/start.py
texpass/controller/__init__.py
texpass/controller/login.py
texpass/controller/register.py
texpass/controller/screen_controller.py
texpass/controller/table_controller.py
texpass/exceptions/__init__.py
texpass/exceptions/exceptions.py
texpass/helper/__init__.py
texpass/helper/account.py
texpass/helper/pass_gen.py
texpass/helper/status.py
texpass/helper/switch_message.py
texpass/helper/timed_string.py
texpass/model/__init__.py
texpass/model/table.py
texpass/screens/__init__.py
texpass/screens/confirm.py
texpass/screens/delete_account.py
texpass/screens/edit_entry.py
texpass/screens/login.py
texpass/screens/new_entry.py
texpass/screens/register.py
texpass/screens/table.py
texpass/styles/__init__.py
texpass/styles/login.tcss
texpass/styles/main_screen.tcss
texpass/styles/modal_screens.tcss
texpass/widgets/__init__.py
texpass/widgets/data_table.py
texpass/widgets/login.py
texpass/widgets/register.py
texpass/widgets/search_input.py
texpass/widgets/submit_input.py
texpass-2.1.0.dist-info/licenses/LICENSE.md
texpass-2.1.0.dist-info/METADATA
texpass-2.1.0.dist-info/WHEEL
texpass-2.1.0.dist-info/entry_points.txt
texpass-2.1.0.dist-info/top_level.txt
texpass-2.1.0.dist-info/RECORD
