Metadata-Version: 2.4
Name: texpass
Version: 2.1.0
Summary: Password manager with Textual user interface
Author-email: Rinceri <rinceri@protonmail.com>
License-Expression: MIT
Project-URL: Homepage, https://github.com/Rinceri/password-manager/
Keywords: password,vault,password manager,textual
Classifier: Programming Language :: Python :: 3
Classifier: Operating System :: OS Independent
License-File: LICENSE.md
Requires-Dist: textual>3.5.0
Requires-Dist: argon2-cffi
Requires-Dist: pyperclip
Requires-Dist: cryptography
Dynamic: license-file
